bot_sort/__init__.py
bot_sort/basetrack.py
bot_sort/bot_sort.py
bot_sort/gmc.py
bot_sort/kalman_filter.py
bot_sort/matching.py
bot_sort/configs/botsort.yaml
bpbreid_strong_sort/__init__.py
bpbreid_strong_sort/ecc.py
bpbreid_strong_sort/strong_sort.py
bpbreid_strong_sort/sort/__init__.py
bpbreid_strong_sort/sort/detection.py
bpbreid_strong_sort/sort/iou_matching.py
bpbreid_strong_sort/sort/kalman_filter.py
bpbreid_strong_sort/sort/linear_assignment.py
bpbreid_strong_sort/sort/nn_matching.py
bpbreid_strong_sort/sort/oks_matching.py
bpbreid_strong_sort/sort/preprocessing.py
bpbreid_strong_sort/sort/track.py
bpbreid_strong_sort/sort/tracker.py
byte_track/__init__.py
byte_track/basetrack.py
byte_track/byte_tracker.py
byte_track/kalman_filter.py
byte_track/matching.py
byte_track/configs/bytetrack.yaml
deep_oc_sort/__init__.py
deep_oc_sort/args.py
deep_oc_sort/association.py
deep_oc_sort/cmc.py
deep_oc_sort/embedding.py
deep_oc_sort/kalmanfilter.py
deep_oc_sort/ocsort.py
deep_oc_sort/reid_multibackend.py
deep_oc_sort/configs/deepocsort.yaml
hydra_plugins/tracklab_searchpath_plugin/__init__.py
hydra_plugins/tracklab_searchpath_plugin/tracklab_searchpath_plugin.py
oc_sort/__init__.py
oc_sort/association.py
oc_sort/kalmanfilter.py
oc_sort/ocsort.py
oc_sort/configs/ocsort.yaml
strong_sort/__init__.py
strong_sort/reid_multibackend.py
strong_sort/strong_sort.py
strong_sort/configs/strongsort.yaml
strong_sort/deep/__init__.py
strong_sort/deep/reid_model_factory.py
strong_sort/deep/models/__init__.py
strong_sort/deep/models/densenet.py
strong_sort/deep/models/hacnn.py
strong_sort/deep/models/inceptionresnetv2.py
strong_sort/deep/models/inceptionv4.py
strong_sort/deep/models/mlfn.py
strong_sort/deep/models/mobilenetv2.py
strong_sort/deep/models/mudeep.py
strong_sort/deep/models/nasnet.py
strong_sort/deep/models/osnet.py
strong_sort/deep/models/osnet_ain.py
strong_sort/deep/models/pcb.py
strong_sort/deep/models/resnet.py
strong_sort/deep/models/resnet_ibn_a.py
tracklab-1.3.23.dist-info/licenses/LICENSE
tracklab-1.3.23.dist-info/METADATA
tracklab-1.3.23.dist-info/WHEEL
tracklab-1.3.23.dist-info/entry_points.txt
tracklab-1.3.23.dist-info/top_level.txt
tracklab-1.3.23.dist-info/RECORD
