Metadata-Version: 2.4
Name: tracklab
Version: 1.3.23
Summary: A Modular End-to-End Tracking Framework for Research and Development
Author-email: Victor Joos <victorjoosdtb@gmail.com>, Baptiste Standaert <baptiste.standaert@uclouvain.be>, Vladimir Somers <vladimir.somers@uclouvain.be>
Requires-Python: >=3.9
License-File: LICENSE
Requires-Dist: hydra-core
Requires-Dist: lightning
Requires-Dist: pytorch_lightning
Requires-Dist: numpy
Requires-Dist: ultralytics
Requires-Dist: filterpy
Requires-Dist: torch
Requires-Dist: torchvision
Requires-Dist: soccernet
Requires-Dist: yt-dlp
Requires-Dist: gdown
Requires-Dist: pandas
Requires-Dist: matplotlib
Requires-Dist: rich
Requires-Dist: tabulate
Requires-Dist: sn-trackeval
Requires-Dist: lap
Requires-Dist: distinctipy
Requires-Dist: rtmlib
Requires-Dist: transformers
Requires-Dist: accelerate
Requires-Dist: huggingface-hub
Requires-Dist: opencv-python
Requires-Dist: tqdm
Requires-Dist: omegaconf
Requires-Dist: requests
Requires-Dist: wandb
Requires-Dist: scipy
Requires-Dist: yacs
Requires-Dist: scikit-image
Dynamic: license-file
